sbc/__init__.py
sbc/sbc_class.py
sbc/util.py
tests/__init__.py
tests/test_SBCclass.py
sbc_classification-0.0.4.dist-info/LICENSE
sbc_classification-0.0.4.dist-info/METADATA
sbc_classification-0.0.4.dist-info/WHEEL
sbc_classification-0.0.4.dist-info/top_level.txt
sbc_classification-0.0.4.dist-info/RECORD
