Metadata-Version: 2.1
Name: sbc-classification
Version: 0.0.4
Summary: Demand Patterns SBC (Syntetos, Boylan, Croston) method of Categorizations
Home-page: https://github.com/tqn14/SBC_classification_python
Author: Thu Nguyen
Author-email: tqn1472@gmail.com
License: MIT License
Keywords: python,demand patterns,sbc classification,croston,idclass,tsintermittent
License-File: LICENSE
Requires-Dist: pandas (>=1.5.3)
Requires-Dist: numpy (>=1.24.4)
Requires-Dist: matplotlib (>=3.7.2)
